claimm/__init__.py
claimm/main.py
claimm/models/__init__.py
claimm/utils/__init__.py
tests/test_main.py
claimm-0.1.3.dist-info/METADATA
claimm-0.1.3.dist-info/WHEEL
claimm-0.1.3.dist-info/top_level.txt
claimm-0.1.3.dist-info/RECORD
